[
    {
        "null": "1",
        "resp_time": 1364609263
    },
    {
        "null": "4",
        "resp_time": 1364609266
    },
    {
        "null": "2",
        "resp_time": 1364609271
    },
    {
        "null": "1",
        "resp_time": 1364609267
    },
    {
        "null": "3",
        "resp_time": 1364856514
    },
    {
        "anxious": "3",
        "calm": "2",
        "conventional": "3",
        "critical": "4",
        "dependable": "3",
        "disorganized": "2",
        "enthusiastic": "2",
        "experiences": "2",
        "reserved": "4",
        "resp_time": 1365458165,
        "sympathetic": "2"
    },
    {
        "null": "2",
        "resp_time": 1365288087
    },
    {
        "null": "null",
        "resp_time": 1365371081
    },
    {
        "anxious": "3",
        "calm": "2",
        "conventional": "3",
        "critical": "5",
        "dependable": "3",
        "disorganized": "3",
        "enthusiastic": "4",
        "experiences": "2",
        "reserved": "4",
        "resp_time": 1366149248,
        "sympathetic": "1"
    },
    {
        "anxious": "2",
        "calm": "4",
        "conventional": "2",
        "critical": "4",
        "dependable": "4",
        "disorganized": "1",
        "enthusiastic": "3",
        "experiences": "2",
        "null": "3",
        "reserved": "2",
        "resp_time": 1366319739,
        "sympathetic": "3"
    },
    {
        "anxious": "1",
        "calm": "4",
        "conventional": "1",
        "critical": "2",
        "dependable": "3",
        "disorganized": "3",
        "enthusiastic": "4",
        "experiences": "2",
        "null": "43.70324765,-72.28959674",
        "reserved": "3",
        "resp_time": 1366595885,
        "sympathetic": "2"
    },
    {
        "anxious": "1",
        "calm": "3",
        "conventional": "1",
        "critical": "3",
        "dependable": "4",
        "disorganized": "2",
        "enthusiastic": "3",
        "experiences": "4",
        "null": "43.70297206,-72.28625376",
        "reserved": "4",
        "resp_time": 1366868361,
        "sympathetic": "1"
    }
]